{
    "revision": "949f8b463330e318d72c3944fe78958b38305cb3",
    "platform": "zenith-staging",
    "result": [
        {
            "suit": "test_runner/performance/test_perf_pgbench_remote.py::test_pg_bench_remote_cluster[5000-10]",
            "total_duration": 133.09789117611945,
            "data": [
                {
                    "name": "scale",
                    "value": 10,
                    "unit": "",
                    "report": "test_param"
                },
                {
                    "name": "number_of_clients",
                    "value": 1,
                    "unit": "",
                    "report": "test_param"
                },
                {
                    "name": "number_of_threads",
                    "value": 1,
                    "unit": "",
                    "report": "test_param"
                },
                {
                    "name": "number_of_transactions_actually_processed",
                    "value": 5000,
                    "unit": "",
                    "report": "test_param"
                },
                {
                    "name": "latency_average",
                    "value": 19.644,
                    "unit": "ms",
                    "report": "lower_is_better"
                },
                {
                    "name": "latency_stddev",
                    "value": 34.601,
                    "unit": "ms",
                    "report": "lower_is_better"
                },
                {
                    "name": "tps_including_connection_time",
                    "value": 50.860498,
                    "unit": "",
                    "report": "higher_is_better"
                },
                {
                    "name": "tps_excluding_connection_time",
                    "value": 50.898834,
                    "unit": "",
                    "report": "higher_is_better"
                },
                {
                    "name": "init_duration",
                    "value": 34.63633578456938,
                    "unit": "s",
                    "report": "lower_is_better"
                },
                {
                    "name": "init_start_timestamp",
                    "value": 1646293111,
                    "unit": "",
                    "report": "test_param"
                },
                {
                    "name": "init_end_timestamp",
                    "value": 1646293146,
                    "unit": "",
                    "report": "test_param"
                },
                {
                    "name": "run_duration",
                    "value": 98.46063102595508,
                    "unit": "s",
                    "report": "lower_is_better"
                },
                {
                    "name": "run_start_timestamp",
                    "value": 1646293146,
                    "unit": "",
                    "report": "test_param"
                },
                {
                    "name": "run_end_timestamp",
                    "value": 1646293245,
                    "unit": "",
                    "report": "test_param"
                }
            ]
        },
        {
            "suit": "test_runner/performance/test_perf_pgbench_remote.py::test_pg_bench_remote_cluster[5000-15]",
            "total_duration": 152.24662127159536,
            "data": [
                {
                    "name": "scale",
                    "value": 15,
                    "unit": "",
                    "report": "test_param"
                },
                {
                    "name": "number_of_clients",
                    "value": 1,
                    "unit": "",
                    "report": "test_param"
                },
                {
                    "name": "number_of_threads",
                    "value": 1,
                    "unit": "",
                    "report": "test_param"
                },
                {
                    "name": "number_of_transactions_actually_processed",
                    "value": 5000,
                    "unit": "",
                    "report": "test_param"
                },
                {
                    "name": "latency_average",
                    "value": 19.95,
                    "unit": "ms",
                    "report": "lower_is_better"
                },
                {
                    "name": "latency_stddev",
                    "value": 35.066,
                    "unit": "ms",
                    "report": "lower_is_better"
                },
                {
                    "name": "tps_including_connection_time",
                    "value": 50.082209,
                    "unit": "",
                    "report": "higher_is_better"
                },
                {
                    "name": "tps_excluding_connection_time",
                    "value": 50.12036,
                    "unit": "",
                    "report": "higher_is_better"
                },
                {
                    "name": "init_duration",
                    "value": 52.29010611958802,
                    "unit": "s",
                    "report": "lower_is_better"
                },
                {
                    "name": "init_start_timestamp",
                    "value": 1646293245,
                    "unit": "",
                    "report": "test_param"
                },
                {
                    "name": "init_end_timestamp",
                    "value": 1646293297,
                    "unit": "",
                    "report": "test_param"
                },
                {
                    "name": "run_duration",
                    "value": 99.95560433156788,
                    "unit": "s",
                    "report": "lower_is_better"
                },
                {
                    "name": "run_start_timestamp",
                    "value": 1646293297,
                    "unit": "",
                    "report": "test_param"
                },
                {
                    "name": "run_end_timestamp",
                    "value": 1646293397,
                    "unit": "",
                    "report": "test_param"
                }
            ]
        },
        {
            "suit": "test_runner/performance/test_perf_pgbench_remote.py::test_pg_bench_remote_cluster[10000-10]",
            "total_duration": 245.19504296407104,
            "data": [
                {
                    "name": "scale",
                    "value": 10,
                    "unit": "",
                    "report": "test_param"
                },
                {
                    "name": "number_of_clients",
                    "value": 1,
                    "unit": "",
                    "report": "test_param"
                },
                {
                    "name": "number_of_threads",
                    "value": 1,
                    "unit": "",
                    "report": "test_param"
                },
                {
                    "name": "number_of_transactions_actually_processed",
                    "value": 10000,
                    "unit": "",
                    "report": "test_param"
                },
                {
                    "name": "latency_average",
                    "value": 20.39,
                    "unit": "ms",
                    "report": "lower_is_better"
                },
                {
                    "name": "latency_stddev",
                    "value": 34.509,
                    "unit": "ms",
                    "report": "lower_is_better"
                },
                {
                    "name": "tps_including_connection_time",
                    "value": 49.017331,
                    "unit": "",
                    "report": "higher_is_better"
                },
                {
                    "name": "tps_excluding_connection_time",
                    "value": 49.037064,
                    "unit": "",
                    "report": "higher_is_better"
                },
                {
                    "name": "init_duration",
                    "value": 41.062980089336634,
                    "unit": "s",
                    "report": "lower_is_better"
                },
                {
                    "name": "init_start_timestamp",
                    "value": 1646293397,
                    "unit": "",
                    "report": "test_param"
                },
                {
                    "name": "init_end_timestamp",
                    "value": 1646293438,
                    "unit": "",
                    "report": "test_param"
                },
                {
                    "name": "run_duration",
                    "value": 204.1311863400042,
                    "unit": "s",
                    "report": "lower_is_better"
                },
                {
                    "name": "run_start_timestamp",
                    "value": 1646293438,
                    "unit": "",
                    "report": "test_param"
                },
                {
                    "name": "run_end_timestamp",
                    "value": 1646293642,
                    "unit": "",
                    "report": "test_param"
                }
            ]
        },
        {
            "suit": "test_runner/performance/test_perf_pgbench_remote.py::test_pg_bench_remote_cluster[10000-15]",
            "total_duration": 247.95782805606723,
            "data": [
                {
                    "name": "scale",
                    "value": 15,
                    "unit": "",
                    "report": "test_param"
                },
                {
                    "name": "number_of_clients",
                    "value": 1,
                    "unit": "",
                    "report": "test_param"
                },
                {
                    "name": "number_of_threads",
                    "value": 1,
                    "unit": "",
                    "report": "test_param"
                },
                {
                    "name": "number_of_transactions_actually_processed",
                    "value": 10000,
                    "unit": "",
                    "report": "test_param"
                },
                {
                    "name": "latency_average",
                    "value": 19.595,
                    "unit": "ms",
                    "report": "lower_is_better"
                },
                {
                    "name": "latency_stddev",
                    "value": 34.972,
                    "unit": "ms",
                    "report": "lower_is_better"
                },
                {
                    "name": "tps_including_connection_time",
                    "value": 51.009451,
                    "unit": "",
                    "report": "higher_is_better"
                },
                {
                    "name": "tps_excluding_connection_time",
                    "value": 51.0287,
                    "unit": "",
                    "report": "higher_is_better"
                },
                {
                    "name": "init_duration",
                    "value": 51.783342372626066,
                    "unit": "s",
                    "report": "lower_is_better"
                },
                {
                    "name": "init_start_timestamp",
                    "value": 1646293642,
                    "unit": "",
                    "report": "test_param"
                },
                {
                    "name": "init_end_timestamp",
                    "value": 1646293694,
                    "unit": "",
                    "report": "test_param"
                },
                {
                    "name": "run_duration",
                    "value": 196.17359201982617,
                    "unit": "s",
                    "report": "lower_is_better"
                },
                {
                    "name": "run_start_timestamp",
                    "value": 1646293694,
                    "unit": "",
                    "report": "test_param"
                },
                {
                    "name": "run_end_timestamp",
                    "value": 1646293890,
                    "unit": "",
                    "report": "test_param"
                }
            ]
        },
        {
            "suit": "test_runner/performance/test_perf_pgbench_remote.py::test_pg_bench_remote_cluster[20000-10]",
            "total_duration": 412.1310203336179,
            "data": [
                {
                    "name": "scale",
                    "value": 10,
                    "unit": "",
                    "report": "test_param"
                },
                {
                    "name": "number_of_clients",
                    "value": 1,
                    "unit": "",
                    "report": "test_param"
                },
                {
                    "name": "number_of_threads",
                    "value": 1,
                    "unit": "",
                    "report": "test_param"
                },
                {
                    "name": "number_of_transactions_actually_processed",
                    "value": 20000,
                    "unit": "",
                    "report": "test_param"
                },
                {
                    "name": "latency_average",
                    "value": 18.963,
                    "unit": "ms",
                    "report": "lower_is_better"
                },
                {
                    "name": "latency_stddev",
                    "value": 35.725,
                    "unit": "ms",
                    "report": "lower_is_better"
                },
                {
                    "name": "tps_including_connection_time",
                    "value": 52.718464,
                    "unit": "",
                    "report": "higher_is_better"
                },
                {
                    "name": "tps_excluding_connection_time",
                    "value": 52.728391,
                    "unit": "",
                    "report": "higher_is_better"
                },
                {
                    "name": "init_duration",
                    "value": 32.61795151606202,
                    "unit": "s",
                    "report": "lower_is_better"
                },
                {
                    "name": "init_start_timestamp",
                    "value": 1646293890,
                    "unit": "",
                    "report": "test_param"
                },
                {
                    "name": "init_end_timestamp",
                    "value": 1646293923,
                    "unit": "",
                    "report": "test_param"
                },
                {
                    "name": "run_duration",
                    "value": 379.51219442486763,
                    "unit": "s",
                    "report": "lower_is_better"
                },
                {
                    "name": "run_start_timestamp",
                    "value": 1646293923,
                    "unit": "",
                    "report": "test_param"
                },
                {
                    "name": "run_end_timestamp",
                    "value": 1646294302,
                    "unit": "",
                    "report": "test_param"
                }
            ]
        },
        {
            "suit": "test_runner/performance/test_perf_pgbench_remote.py::test_pg_bench_remote_cluster[20000-15]",
            "total_duration": 440.8753607645631,
            "data": [
                {
                    "name": "scale",
                    "value": 15,
                    "unit": "",
                    "report": "test_param"
                },
                {
                    "name": "number_of_clients",
                    "value": 1,
                    "unit": "",
                    "report": "test_param"
                },
                {
                    "name": "number_of_threads",
                    "value": 1,
                    "unit": "",
                    "report": "test_param"
                },
                {
                    "name": "number_of_transactions_actually_processed",
                    "value": 20000,
                    "unit": "",
                    "report": "test_param"
                },
                {
                    "name": "latency_average",
                    "value": 19.02,
                    "unit": "ms",
                    "report": "lower_is_better"
                },
                {
                    "name": "latency_stddev",
                    "value": 30.844,
                    "unit": "ms",
                    "report": "lower_is_better"
                },
                {
                    "name": "tps_including_connection_time",
                    "value": 52.559608,
                    "unit": "",
                    "report": "higher_is_better"
                },
                {
                    "name": "tps_excluding_connection_time",
                    "value": 52.570472,
                    "unit": "",
                    "report": "higher_is_better"
                },
                {
                    "name": "init_duration",
                    "value": 60.21870289929211,
                    "unit": "s",
                    "report": "lower_is_better"
                },
                {
                    "name": "init_start_timestamp",
                    "value": 1646294302,
                    "unit": "",
                    "report": "test_param"
                },
                {
                    "name": "init_end_timestamp",
                    "value": 1646294362,
                    "unit": "",
                    "report": "test_param"
                },
                {
                    "name": "run_duration",
                    "value": 380.65576750040054,
                    "unit": "s",
                    "report": "lower_is_better"
                },
                {
                    "name": "run_start_timestamp",
                    "value": 1646294362,
                    "unit": "",
                    "report": "test_param"
                },
                {
                    "name": "run_end_timestamp",
                    "value": 1646294743,
                    "unit": "",
                    "report": "test_param"
                }
            ]
        }
    ]
}