{
    "revision": "52f445094aa722dff377b36995b9562f752302cf",
    "platform": "zenith-local-ci",
    "result": [
        {
            "suit": "test_runner/performance/test_bulk_insert.py::test_bulk_insert[vanilla]",
            "total_duration": 3.8380038749892265,
            "data": [
                {
                    "name": "insert",
                    "value": 3.823179804996471,
                    "unit": "s",
                    "report": "lower_is_better"
                },
                {
                    "name": "data_size",
                    "value": 196.73612308502197,
                    "unit": "MB",
                    "report": "lower_is_better"
                },
                {
                    "name": "wal_size",
                    "value": 352.0,
                    "unit": "MB",
                    "report": "lower_is_better"
                }
            ]
        },
        {
            "suit": "test_runner/performance/test_bulk_insert.py::test_bulk_insert[neon]",
            "total_duration": 18.579744403003133,
            "data": [
                {
                    "name": "insert",
                    "value": 17.652924134003115,
                    "unit": "s",
                    "report": "lower_is_better"
                },
                {
                    "name": "pageserver_writes",
                    "value": 873,
                    "unit": "MB",
                    "report": "lower_is_better"
                },
                {
                    "name": "peak_mem",
                    "value": 207.9296875,
                    "unit": "MB",
                    "report": "lower_is_better"
                },
                {
                    "name": "size",
                    "value": 472.64111328125,
                    "unit": "MB",
                    "report": "lower_is_better"
                },
                {
                    "name": "data_uploaded",
                    "value": 471.5,
                    "unit": "MB",
                    "report": "lower_is_better"
                },
                {
                    "name": "num_files_uploaded",
                    "value": 2,
                    "unit": "",
                    "report": "lower_is_better"
                }
            ]
        },
        {
            "suit": "test_runner/performance/test_bulk_tenant_create.py::test_bulk_tenant_create[1]",
            "total_duration": 3.0299305689986795,
            "data": [
                {
                    "name": "tenant_creation_time",
                    "value": 1.801131621003151,
                    "unit": "s",
                    "report": "lower_is_better"
                }
            ]
        },
        {
            "suit": "test_runner/performance/test_bulk_tenant_create.py::test_bulk_tenant_create[5]",
            "total_duration": 9.332144548010547,
            "data": [
                {
                    "name": "tenant_creation_time",
                    "value": 1.5623790086014195,
                    "unit": "s",
                    "report": "lower_is_better"
                }
            ]
        },
        {
            "suit": "test_runner/performance/test_bulk_tenant_create.py::test_bulk_tenant_create[10]",
            "total_duration": 19.15581245800422,
            "data": [
                {
                    "name": "tenant_creation_time",
                    "value": 1.7009346347025711,
                    "unit": "s",
                    "report": "lower_is_better"
                }
            ]
        },
        {
            "suit": "test_runner/performance/test_compare_pg_stats.py::test_compare_pg_stats_rw_with_pgbench_default[vanilla-5-10-100]",
            "total_duration": 6.811418109005899,
            "data": [
                {
                    "name": "pg_stat_database.tup_deleted",
                    "value": 0,
                    "unit": "",
                    "report": "higher_is_better"
                },
                {
                    "name": "pg_stat_database.tup_updated",
                    "value": 34900,
                    "unit": "",
                    "report": "higher_is_better"
                },
                {
                    "name": "pg_stat_database.tup_returned",
                    "value": 1313696,
                    "unit": "",
                    "report": "higher_is_better"
                },
                {
                    "name": "pg_stat_database.tup_inserted",
                    "value": 11633,
                    "unit": "",
                    "report": "higher_is_better"
                },
                {
                    "name": "pg_stat_database.tup_fetched",
                    "value": 24002,
                    "unit": "",
                    "report": "higher_is_better"
                }
            ]
        },
        {
            "suit": "test_runner/performance/test_compare_pg_stats.py::test_compare_pg_stats_rw_with_pgbench_default[neon-5-10-100]",
            "total_duration": 11.321744936998584,
            "data": [
                {
                    "name": "pg_stat_database.tup_deleted",
                    "value": 0,
                    "unit": "",
                    "report": "higher_is_better"
                },
                {
                    "name": "pg_stat_database.tup_updated",
                    "value": 22948,
                    "unit": "",
                    "report": "higher_is_better"
                },
                {
                    "name": "pg_stat_database.tup_returned",
                    "value": 865203,
                    "unit": "",
                    "report": "higher_is_better"
                },
                {
                    "name": "pg_stat_database.tup_inserted",
                    "value": 7649,
                    "unit": "",
                    "report": "higher_is_better"
                },
                {
                    "name": "pg_stat_database.tup_fetched",
                    "value": 16034,
                    "unit": "",
                    "report": "higher_is_better"
                }
            ]
        },
        {
            "suit": "test_runner/performance/test_compare_pg_stats.py::test_compare_pg_stats_wo_with_pgbench_simple_update[vanilla-5-10-100]",
            "total_duration": 6.756719256009092,
            "data": [
                {
                    "name": "pg_stat_database.tup_inserted",
                    "value": 18493,
                    "unit": "",
                    "report": "higher_is_better"
                },
                {
                    "name": "pg_stat_database.tup_deleted",
                    "value": 0,
                    "unit": "",
                    "report": "higher_is_better"
                },
                {
                    "name": "pg_stat_database.tup_updated",
                    "value": 18494,
                    "unit": "",
                    "report": "higher_is_better"
                }
            ]
        },
        {
            "suit": "test_runner/performance/test_compare_pg_stats.py::test_compare_pg_stats_wo_with_pgbench_simple_update[neon-5-10-100]",
            "total_duration": 11.062552442002925,
            "data": [
                {
                    "name": "pg_stat_database.tup_inserted",
                    "value": 10214,
                    "unit": "",
                    "report": "higher_is_better"
                },
                {
                    "name": "pg_stat_database.tup_deleted",
                    "value": 0,
                    "unit": "",
                    "report": "higher_is_better"
                },
                {
                    "name": "pg_stat_database.tup_updated",
                    "value": 10215,
                    "unit": "",
                    "report": "higher_is_better"
                }
            ]
        },
        {
            "suit": "test_runner/performance/test_compare_pg_stats.py::test_compare_pg_stats_ro_with_pgbench_select_only[vanilla-5-10-100]",
            "total_duration": 6.684322966000764,
            "data": [
                {
                    "name": "pg_stat_database.tup_returned",
                    "value": 80667,
                    "unit": "",
                    "report": "higher_is_better"
                },
                {
                    "name": "pg_stat_database.tup_fetched",
                    "value": 79034,
                    "unit": "",
                    "report": "higher_is_better"
                }
            ]
        },
        {
            "suit": "test_runner/performance/test_compare_pg_stats.py::test_compare_pg_stats_ro_with_pgbench_select_only[neon-5-10-100]",
            "total_duration": 11.008171102002962,
            "data": [
                {
                    "name": "pg_stat_database.tup_returned",
                    "value": 27272,
                    "unit": "",
                    "report": "higher_is_better"
                },
                {
                    "name": "pg_stat_database.tup_fetched",
                    "value": 25639,
                    "unit": "",
                    "report": "higher_is_better"
                }
            ]
        },
        {
            "suit": "test_runner/performance/test_compare_pg_stats.py::test_compare_pg_stats_wal_with_pgbench_default[vanilla-5-10-100]",
            "total_duration": 6.7767345379979815,
            "data": [
                {
                    "name": "pg_stat_wal.wal_write",
                    "value": 7448,
                    "unit": "",
                    "report": "higher_is_better"
                },
                {
                    "name": "pg_stat_wal.wal_buffers_full",
                    "value": 0,
                    "unit": "",
                    "report": "higher_is_better"
                },
                {
                    "name": "pg_stat_wal.wal_fpi",
                    "value": 10353,
                    "unit": "",
                    "report": "higher_is_better"
                },
                {
                    "name": "pg_stat_wal.wal_bytes",
                    "value": 87429104,
                    "unit": "",
                    "report": "higher_is_better"
                },
                {
                    "name": "pg_stat_wal.wal_records",
                    "value": 70024,
                    "unit": "",
                    "report": "higher_is_better"
                }
            ]
        },
        {
            "suit": "test_runner/performance/test_compare_pg_stats.py::test_compare_pg_stats_wal_with_pgbench_default[neon-5-10-100]",
            "total_duration": 11.615447097996366,
            "data": [
                {
                    "name": "pg_stat_wal.wal_write",
                    "value": 7175,
                    "unit": "",
                    "report": "higher_is_better"
                },
                {
                    "name": "pg_stat_wal.wal_buffers_full",
                    "value": 0,
                    "unit": "",
                    "report": "higher_is_better"
                },
                {
                    "name": "pg_stat_wal.wal_fpi",
                    "value": 109,
                    "unit": "",
                    "report": "higher_is_better"
                },
                {
                    "name": "pg_stat_wal.wal_bytes",
                    "value": 4793808,
                    "unit": "",
                    "report": "higher_is_better"
                },
                {
                    "name": "pg_stat_wal.wal_records",
                    "value": 47898,
                    "unit": "",
                    "report": "higher_is_better"
                }
            ]
        },
        {
            "suit": "test_runner/performance/test_copy.py::test_copy[vanilla]",
            "total_duration": 4.383154344992363,
            "data": [
                {
                    "name": "copy_extend",
                    "value": 1.50269514300453,
                    "unit": "s",
                    "report": "lower_is_better"
                },
                {
                    "name": "delete",
                    "value": 0.8426589480077382,
                    "unit": "s",
                    "report": "lower_is_better"
                },
                {
                    "name": "vacuum",
                    "value": 0.22419346700189635,
                    "unit": "s",
                    "report": "lower_is_better"
                },
                {
                    "name": "copy_reuse",
                    "value": 1.6716671950125601,
                    "unit": "s",
                    "report": "lower_is_better"
                },
                {
                    "name": "data_size",
                    "value": 97.63456058502197,
                    "unit": "MB",
                    "report": "lower_is_better"
                },
                {
                    "name": "wal_size",
                    "value": 144.0,
                    "unit": "MB",
                    "report": "lower_is_better"
                }
            ]
        },
        {
            "suit": "test_runner/performance/test_copy.py::test_copy[neon]",
            "total_duration": 11.762877991990536,
            "data": [
                {
                    "name": "copy_extend",
                    "value": 1.754185380996205,
                    "unit": "s",
                    "report": "lower_is_better"
                },
                {
                    "name": "copy_extend_pageserver_writes",
                    "value": 99,
                    "unit": "MB",
                    "report": "lower_is_better"
                },
                {
                    "name": "delete",
                    "value": 4.219463451998308,
                    "unit": "s",
                    "report": "lower_is_better"
                },
                {
                    "name": "delete_pageserver_writes",
                    "value": 148,
                    "unit": "MB",
                    "report": "lower_is_better"
                },
                {
                    "name": "vacuum",
                    "value": 1.8880008150008507,
                    "unit": "s",
                    "report": "lower_is_better"
                },
                {
                    "name": "vacuum_pageserver_writes",
                    "value": 13,
                    "unit": "MB",
                    "report": "lower_is_better"
                },
                {
                    "name": "copy_reuse",
                    "value": 3.036545966999256,
                    "unit": "s",
                    "report": "lower_is_better"
                },
                {
                    "name": "copy_reuse_pageserver_writes",
                    "value": 123,
                    "unit": "MB",
                    "report": "lower_is_better"
                },
                {
                    "name": "peak_mem",
                    "value": 118.38671875,
                    "unit": "MB",
                    "report": "lower_is_better"
                },
                {
                    "name": "size",
                    "value": 217.15673828125,
                    "unit": "MB",
                    "report": "lower_is_better"
                },
                {
                    "name": "data_uploaded",
                    "value": 217.15625,
                    "unit": "MB",
                    "report": "lower_is_better"
                },
                {
                    "name": "num_files_uploaded",
                    "value": 4,
                    "unit": "",
                    "report": "lower_is_better"
                }
            ]
        },
        {
            "suit": "test_runner/performance/test_gist_build.py::test_gist_buffering_build[vanilla]",
            "total_duration": 9.912184389002505,
            "data": [
                {
                    "name": "build",
                    "value": 8.498042492006789,
                    "unit": "s",
                    "report": "lower_is_better"
                },
                {
                    "name": "data_size",
                    "value": 167.97049808502197,
                    "unit": "MB",
                    "report": "lower_is_better"
                },
                {
                    "name": "wal_size",
                    "value": 144.0,
                    "unit": "MB",
                    "report": "lower_is_better"
                }
            ]
        },
        {
            "suit": "test_runner/performance/test_gist_build.py::test_gist_buffering_build[neon]",
            "total_duration": 15.527710266993381,
            "data": [
                {
                    "name": "build",
                    "value": 10.610533441998996,
                    "unit": "s",
                    "report": "lower_is_better"
                },
                {
                    "name": "pageserver_writes",
                    "value": 365,
                    "unit": "MB",
                    "report": "lower_is_better"
                },
                {
                    "name": "peak_mem",
                    "value": 127.59765625,
                    "unit": "MB",
                    "report": "lower_is_better"
                },
                {
                    "name": "size",
                    "value": 204.96142578125,
                    "unit": "MB",
                    "report": "lower_is_better"
                },
                {
                    "name": "data_uploaded",
                    "value": 204.9609375,
                    "unit": "MB",
                    "report": "lower_is_better"
                },
                {
                    "name": "num_files_uploaded",
                    "value": 1,
                    "unit": "",
                    "report": "lower_is_better"
                }
            ]
        },
        {
            "suit": "test_runner/performance/test_parallel_copy_to.py::test_parallel_copy_different_tables[vanilla]",
            "total_duration": 19.684703676000936,
            "data": [
                {
                    "name": "load",
                    "value": 19.660862677003024,
                    "unit": "s",
                    "report": "lower_is_better"
                },
                {
                    "name": "data_size",
                    "value": 2244.009560585022,
                    "unit": "MB",
                    "report": "lower_is_better"
                },
                {
                    "name": "wal_size",
                    "value": 560.0,
                    "unit": "MB",
                    "report": "lower_is_better"
                }
            ]
        },
        {
            "suit": "test_runner/performance/test_parallel_copy_to.py::test_parallel_copy_different_tables[neon]",
            "total_duration": 19.77317153700278,
            "data": [
                {
                    "name": "load",
                    "value": 18.290751503998763,
                    "unit": "s",
                    "report": "lower_is_better"
                },
                {
                    "name": "pageserver_writes",
                    "value": 3642,
                    "unit": "MB",
                    "report": "lower_is_better"
                },
                {
                    "name": "peak_mem",
                    "value": 132.54296875,
                    "unit": "MB",
                    "report": "lower_is_better"
                },
                {
                    "name": "size",
                    "value": 1803.26611328125,
                    "unit": "MB",
                    "report": "lower_is_better"
                },
                {
                    "name": "data_uploaded",
                    "value": 1803.1640625,
                    "unit": "MB",
                    "report": "lower_is_better"
                },
                {
                    "name": "num_files_uploaded",
                    "value": 7,
                    "unit": "",
                    "report": "lower_is_better"
                }
            ]
        },
        {
            "suit": "test_runner/performance/test_parallel_copy_to.py::test_parallel_copy_same_table[vanilla]",
            "total_duration": 13.563870922007482,
            "data": [
                {
                    "name": "load",
                    "value": 13.549507727002492,
                    "unit": "s",
                    "report": "lower_is_better"
                },
                {
                    "name": "data_size",
                    "value": 2243.861123085022,
                    "unit": "MB",
                    "report": "lower_is_better"
                },
                {
                    "name": "wal_size",
                    "value": 592.0,
                    "unit": "MB",
                    "report": "lower_is_better"
                }
            ]
        },
        {
            "suit": "test_runner/performance/test_parallel_copy_to.py::test_parallel_copy_same_table[neon]",
            "total_duration": 24.16793825700006,
            "data": [
                {
                    "name": "load",
                    "value": 23.241008886994678,
                    "unit": "s",
                    "report": "lower_is_better"
                },
                {
                    "name": "pageserver_writes",
                    "value": 7308,
                    "unit": "MB",
                    "report": "lower_is_better"
                },
                {
                    "name": "peak_mem",
                    "value": 115.46875,
                    "unit": "MB",
                    "report": "lower_is_better"
                },
                {
                    "name": "size",
                    "value": 3658.69580078125,
                    "unit": "MB",
                    "report": "lower_is_better"
                },
                {
                    "name": "data_uploaded",
                    "value": 3658.6953125,
                    "unit": "MB",
                    "report": "lower_is_better"
                },
                {
                    "name": "num_files_uploaded",
                    "value": 7,
                    "unit": "",
                    "report": "lower_is_better"
                }
            ]
        },
        {
            "suit": "test_runner/performance/test_perf_pgbench.py::test_pgbench[vanilla-45-10]",
            "total_duration": 93.01946179699735,
            "data": [
                {
                    "name": "scale",
                    "value": 10,
                    "unit": "",
                    "report": "test_param"
                },
                {
                    "name": "init.duration",
                    "value": 2.749282275006408,
                    "unit": "s",
                    "report": "lower_is_better"
                },
                {
                    "name": "init.start_timestamp",
                    "value": 1657285591,
                    "unit": "",
                    "report": "test_param"
                },
                {
                    "name": "init.end_timestamp",
                    "value": 1657285593,
                    "unit": "",
                    "report": "test_param"
                },
                {
                    "name": "simple-update.number_of_clients",
                    "value": 4,
                    "unit": "",
                    "report": "test_param"
                },
                {
                    "name": "simple-update.number_of_threads",
                    "value": 1,
                    "unit": "",
                    "report": "test_param"
                },
                {
                    "name": "simple-update.number_of_transactions_actually_processed",
                    "value": 527811,
                    "unit": "",
                    "report": "test_param"
                },
                {
                    "name": "simple-update.latency_average",
                    "value": 0.338,
                    "unit": "ms",
                    "report": "lower_is_better"
                },
                {
                    "name": "simple-update.latency_stddev",
                    "value": 0.921,
                    "unit": "ms",
                    "report": "lower_is_better"
                },
                {
                    "name": "simple-update.tps",
                    "value": 11732.332871,
                    "unit": "",
                    "report": "higher_is_better"
                },
                {
                    "name": "simple-update.run_duration",
                    "value": 45.02343096100958,
                    "unit": "s",
                    "report": "lower_is_better"
                },
                {
                    "name": "simple-update.run_start_timestamp",
                    "value": 1657285593,
                    "unit": "",
                    "report": "test_param"
                },
                {
                    "name": "simple-update.run_end_timestamp",
                    "value": 1657285638,
                    "unit": "",
                    "report": "test_param"
                },
                {
                    "name": "select-only.number_of_clients",
                    "value": 4,
                    "unit": "",
                    "report": "test_param"
                },
                {
                    "name": "select-only.number_of_threads",
                    "value": 1,
                    "unit": "",
                    "report": "test_param"
                },
                {
                    "name": "select-only.number_of_transactions_actually_processed",
                    "value": 2413538,
                    "unit": "",
                    "report": "test_param"
                },
                {
                    "name": "select-only.latency_average",
                    "value": 0.073,
                    "unit": "ms",
                    "report": "lower_is_better"
                },
                {
                    "name": "select-only.latency_stddev",
                    "value": 0.05,
                    "unit": "ms",
                    "report": "lower_is_better"
                },
                {
                    "name": "select-only.tps",
                    "value": 53643.543941,
                    "unit": "",
                    "report": "higher_is_better"
                },
                {
                    "name": "select-only.run_duration",
                    "value": 45.02515460801078,
                    "unit": "s",
                    "report": "lower_is_better"
                },
                {
                    "name": "select-only.run_start_timestamp",
                    "value": 1657285639,
                    "unit": "",
                    "report": "test_param"
                },
                {
                    "name": "select-only.run_end_timestamp",
                    "value": 1657285684,
                    "unit": "",
                    "report": "test_param"
                },
                {
                    "name": "data_size",
                    "value": 175.94706058502197,
                    "unit": "MB",
                    "report": "lower_is_better"
                },
                {
                    "name": "wal_size",
                    "value": 304.0,
                    "unit": "MB",
                    "report": "lower_is_better"
                }
            ]
        },
        {
            "suit": "test_runner/performance/test_perf_pgbench.py::test_pgbench[neon-45-10]",
            "total_duration": 97.28359138099768,
            "data": [
                {
                    "name": "scale",
                    "value": 10,
                    "unit": "",
                    "report": "test_param"
                },
                {
                    "name": "init.pageserver_writes",
                    "value": 254,
                    "unit": "MB",
                    "report": "lower_is_better"
                },
                {
                    "name": "init.duration",
                    "value": 6.237864370996249,
                    "unit": "s",
                    "report": "lower_is_better"
                },
                {
                    "name": "init.start_timestamp",
                    "value": 1657285685,
                    "unit": "",
                    "report": "test_param"
                },
                {
                    "name": "init.end_timestamp",
                    "value": 1657285691,
                    "unit": "",
                    "report": "test_param"
                },
                {
                    "name": "simple-update.pageserver_writes",
                    "value": 169,
                    "unit": "MB",
                    "report": "lower_is_better"
                },
                {
                    "name": "simple-update.number_of_clients",
                    "value": 4,
                    "unit": "",
                    "report": "test_param"
                },
                {
                    "name": "simple-update.number_of_threads",
                    "value": 1,
                    "unit": "",
                    "report": "test_param"
                },
                {
                    "name": "simple-update.number_of_transactions_actually_processed",
                    "value": 178496,
                    "unit": "",
                    "report": "test_param"
                },
                {
                    "name": "simple-update.latency_average",
                    "value": 1.005,
                    "unit": "ms",
                    "report": "lower_is_better"
                },
                {
                    "name": "simple-update.latency_stddev",
                    "value": 2.138,
                    "unit": "ms",
                    "report": "lower_is_better"
                },
                {
                    "name": "simple-update.tps",
                    "value": 3967.460846,
                    "unit": "",
                    "report": "higher_is_better"
                },
                {
                    "name": "simple-update.run_duration",
                    "value": 45.03763589001028,
                    "unit": "s",
                    "report": "lower_is_better"
                },
                {
                    "name": "simple-update.run_start_timestamp",
                    "value": 1657285691,
                    "unit": "",
                    "report": "test_param"
                },
                {
                    "name": "simple-update.run_end_timestamp",
                    "value": 1657285736,
                    "unit": "",
                    "report": "test_param"
                },
                {
                    "name": "select-only.pageserver_writes",
                    "value": 1,
                    "unit": "MB",
                    "report": "lower_is_better"
                },
                {
                    "name": "select-only.number_of_clients",
                    "value": 4,
                    "unit": "",
                    "report": "test_param"
                },
                {
                    "name": "select-only.number_of_threads",
                    "value": 1,
                    "unit": "",
                    "report": "test_param"
                },
                {
                    "name": "select-only.number_of_transactions_actually_processed",
                    "value": 399467,
                    "unit": "",
                    "report": "test_param"
                },
                {
                    "name": "select-only.latency_average",
                    "value": 0.45,
                    "unit": "ms",
                    "report": "lower_is_better"
                },
                {
                    "name": "select-only.latency_stddev",
                    "value": 0.305,
                    "unit": "ms",
                    "report": "lower_is_better"
                },
                {
                    "name": "select-only.tps",
                    "value": 8879.210577,
                    "unit": "",
                    "report": "higher_is_better"
                },
                {
                    "name": "select-only.run_duration",
                    "value": 45.04010864200245,
                    "unit": "s",
                    "report": "lower_is_better"
                },
                {
                    "name": "select-only.run_start_timestamp",
                    "value": 1657285737,
                    "unit": "",
                    "report": "test_param"
                },
                {
                    "name": "select-only.run_end_timestamp",
                    "value": 1657285782,
                    "unit": "",
                    "report": "test_param"
                },
                {
                    "name": "size",
                    "value": 211.75830078125,
                    "unit": "MB",
                    "report": "lower_is_better"
                },
                {
                    "name": "data_uploaded",
                    "value": 211.7578125,
                    "unit": "MB",
                    "report": "lower_is_better"
                },
                {
                    "name": "num_files_uploaded",
                    "value": 3,
                    "unit": "",
                    "report": "lower_is_better"
                }
            ]
        },
        {
            "suit": "test_runner/performance/test_perf_pgbench.py::test_pgbench_flamegraph[45-10]",
            "total_duration": 98.36801752100291,
            "data": [
                {
                    "name": "scale",
                    "value": 10,
                    "unit": "",
                    "report": "test_param"
                },
                {
                    "name": "init.pageserver_writes",
                    "value": 254,
                    "unit": "MB",
                    "report": "lower_is_better"
                },
                {
                    "name": "init.duration",
                    "value": 6.181932888008305,
                    "unit": "s",
                    "report": "lower_is_better"
                },
                {
                    "name": "init.start_timestamp",
                    "value": 1657285786,
                    "unit": "",
                    "report": "test_param"
                },
                {
                    "name": "init.end_timestamp",
                    "value": 1657285792,
                    "unit": "",
                    "report": "test_param"
                },
                {
                    "name": "simple-update.pageserver_writes",
                    "value": 171,
                    "unit": "MB",
                    "report": "lower_is_better"
                },
                {
                    "name": "simple-update.number_of_clients",
                    "value": 4,
                    "unit": "",
                    "report": "test_param"
                },
                {
                    "name": "simple-update.number_of_threads",
                    "value": 1,
                    "unit": "",
                    "report": "test_param"
                },
                {
                    "name": "simple-update.number_of_transactions_actually_processed",
                    "value": 202383,
                    "unit": "",
                    "report": "test_param"
                },
                {
                    "name": "simple-update.latency_average",
                    "value": 0.888,
                    "unit": "ms",
                    "report": "lower_is_better"
                },
                {
                    "name": "simple-update.latency_stddev",
                    "value": 2.652,
                    "unit": "ms",
                    "report": "lower_is_better"
                },
                {
                    "name": "simple-update.tps",
                    "value": 4495.744267,
                    "unit": "",
                    "report": "higher_is_better"
                },
                {
                    "name": "simple-update.run_duration",
                    "value": 45.05664480700216,
                    "unit": "s",
                    "report": "lower_is_better"
                },
                {
                    "name": "simple-update.run_start_timestamp",
                    "value": 1657285792,
                    "unit": "",
                    "report": "test_param"
                },
                {
                    "name": "simple-update.run_end_timestamp",
                    "value": 1657285837,
                    "unit": "",
                    "report": "test_param"
                },
                {
                    "name": "select-only.pageserver_writes",
                    "value": 1,
                    "unit": "MB",
                    "report": "lower_is_better"
                },
                {
                    "name": "select-only.number_of_clients",
                    "value": 4,
                    "unit": "",
                    "report": "test_param"
                },
                {
                    "name": "select-only.number_of_threads",
                    "value": 1,
                    "unit": "",
                    "report": "test_param"
                },
                {
                    "name": "select-only.number_of_transactions_actually_processed",
                    "value": 462846,
                    "unit": "",
                    "report": "test_param"
                },
                {
                    "name": "select-only.latency_average",
                    "value": 0.388,
                    "unit": "ms",
                    "report": "lower_is_better"
                },
                {
                    "name": "select-only.latency_stddev",
                    "value": 0.346,
                    "unit": "ms",
                    "report": "lower_is_better"
                },
                {
                    "name": "select-only.tps",
                    "value": 10287.328902,
                    "unit": "",
                    "report": "higher_is_better"
                },
                {
                    "name": "select-only.run_duration",
                    "value": 45.03100181899208,
                    "unit": "s",
                    "report": "lower_is_better"
                },
                {
                    "name": "select-only.run_start_timestamp",
                    "value": 1657285837,
                    "unit": "",
                    "report": "test_param"
                },
                {
                    "name": "select-only.run_end_timestamp",
                    "value": 1657285882,
                    "unit": "",
                    "report": "test_param"
                },
                {
                    "name": "size",
                    "value": 217.74267578125,
                    "unit": "MB",
                    "report": "lower_is_better"
                },
                {
                    "name": "data_uploaded",
                    "value": 217.7421875,
                    "unit": "MB",
                    "report": "lower_is_better"
                },
                {
                    "name": "num_files_uploaded",
                    "value": 3,
                    "unit": "",
                    "report": "lower_is_better"
                }
            ]
        },
        {
            "suit": "test_runner/performance/test_random_writes.py::test_random_writes[vanilla]",
            "total_duration": 1.6281052560079843,
            "data": [
                {
                    "name": "init",
                    "value": 1.5711039759917185,
                    "unit": "s",
                    "report": "lower_is_better"
                },
                {
                    "name": "table_size",
                    "value": 36249600,
                    "unit": "bytes",
                    "report": "test_param"
                },
                {
                    "name": "effective_checkpoint_distance",
                    "value": 36,
                    "unit": "bytes",
                    "report": "test_param"
                },
                {
                    "name": "run",
                    "value": 0.05386166700918693,
                    "unit": "s",
                    "report": "lower_is_better"
                }
            ]
        },
        {
            "suit": "test_runner/performance/test_random_writes.py::test_random_writes[neon]",
            "total_duration": 7.561862653004937,
            "data": [
                {
                    "name": "init",
                    "value": 6.585652708003181,
                    "unit": "s",
                    "report": "lower_is_better"
                },
                {
                    "name": "table_size",
                    "value": 36249600,
                    "unit": "bytes",
                    "report": "test_param"
                },
                {
                    "name": "effective_checkpoint_distance",
                    "value": 36,
                    "unit": "bytes",
                    "report": "test_param"
                },
                {
                    "name": "run",
                    "value": 0.9679989410069538,
                    "unit": "s",
                    "report": "lower_is_better"
                }
            ]
        },
        {
            "suit": "test_runner/performance/test_seqscans.py::test_seqscans[vanilla-100000-100-0]",
            "total_duration": 0.6105761199869448,
            "data": [
                {
                    "name": "table_size",
                    "value": 3629056,
                    "unit": "bytes",
                    "report": "test_param"
                },
                {
                    "name": "run",
                    "value": 0.5505830540059833,
                    "unit": "s",
                    "report": "lower_is_better"
                }
            ]
        },
        {
            "suit": "test_runner/performance/test_seqscans.py::test_seqscans[vanilla-10000000-1-0]",
            "total_duration": 7.522347706995788,
            "data": [
                {
                    "name": "table_size",
                    "value": 362479616,
                    "unit": "bytes",
                    "report": "test_param"
                },
                {
                    "name": "run",
                    "value": 0.7939809010131285,
                    "unit": "s",
                    "report": "lower_is_better"
                }
            ]
        },
        {
            "suit": "test_runner/performance/test_seqscans.py::test_seqscans[vanilla-10000000-1-4]",
            "total_duration": 7.615393888001563,
            "data": [
                {
                    "name": "table_size",
                    "value": 362479616,
                    "unit": "bytes",
                    "report": "test_param"
                },
                {
                    "name": "run",
                    "value": 0.2795328350039199,
                    "unit": "s",
                    "report": "lower_is_better"
                }
            ]
        },
        {
            "suit": "test_runner/performance/test_seqscans.py::test_seqscans[neon-100000-100-0]",
            "total_duration": 3.4975775909988442,
            "data": [
                {
                    "name": "table_size",
                    "value": 3629056,
                    "unit": "bytes",
                    "report": "test_param"
                },
                {
                    "name": "run",
                    "value": 1.8809538519999478,
                    "unit": "s",
                    "report": "lower_is_better"
                }
            ]
        },
        {
            "suit": "test_runner/performance/test_seqscans.py::test_seqscans[neon-10000000-1-0]",
            "total_duration": 43.79009533699718,
            "data": [
                {
                    "name": "table_size",
                    "value": 362479616,
                    "unit": "bytes",
                    "report": "test_param"
                },
                {
                    "name": "run",
                    "value": 12.283673040001304,
                    "unit": "s",
                    "report": "lower_is_better"
                }
            ]
        },
        {
            "suit": "test_runner/performance/test_seqscans.py::test_seqscans[neon-10000000-1-4]",
            "total_duration": 40.246239747997606,
            "data": [
                {
                    "name": "table_size",
                    "value": 362479616,
                    "unit": "bytes",
                    "report": "test_param"
                },
                {
                    "name": "run",
                    "value": 8.661231050995411,
                    "unit": "s",
                    "report": "lower_is_better"
                }
            ]
        },
        {
            "suit": "test_runner/performance/test_startup.py::test_startup",
            "total_duration": 248.3932347480004,
            "data": [
                {
                    "name": "startup_time",
                    "value": 0.1749101699970197,
                    "unit": "s",
                    "report": "lower_is_better"
                },
                {
                    "name": "restart_time",
                    "value": 0.8104360299912514,
                    "unit": "s",
                    "report": "lower_is_better"
                },
                {
                    "name": "read_time",
                    "value": 1.78445972398913,
                    "unit": "s",
                    "report": "lower_is_better"
                },
                {
                    "name": "second_read_time",
                    "value": 0.744573596995906,
                    "unit": "s",
                    "report": "lower_is_better"
                },
                {
                    "name": "restart_with_data",
                    "value": 0.20955937600228935,
                    "unit": "s",
                    "report": "lower_is_better"
                },
                {
                    "name": "read_after_restart",
                    "value": 0.6665308899973752,
                    "unit": "s",
                    "report": "lower_is_better"
                }
            ]
        },
        {
            "suit": "test_runner/performance/test_wal_backpressure.py::test_heavy_write_workload[vanilla-10-5-5]",
            "total_duration": 36.0908025020035,
            "data": [
                {
                    "name": "run_duration",
                    "value": 35.11331147700548,
                    "unit": "s",
                    "report": "lower_is_better"
                },
                {
                    "name": "read_latency_max",
                    "value": 0.009213866011123173,
                    "unit": "s",
                    "report": "lower_is_better"
                },
                {
                    "name": "read_latency_avg",
                    "value": 0.0008211864725227416,
                    "unit": "s",
                    "report": "lower_is_better"
                },
                {
                    "name": "read_latency_stdev",
                    "value": 0.0015586815755991342,
                    "unit": "s",
                    "report": "lower_is_better"
                }
            ]
        },
        {
            "suit": "test_runner/performance/test_wal_backpressure.py::test_heavy_write_workload[neon_off-10-5-5]",
            "total_duration": 229.4936825610057,
            "data": [
                {
                    "name": "run_duration",
                    "value": 227.3497913799947,
                    "unit": "s",
                    "report": "lower_is_better"
                },
                {
                    "name": "lsn_write_lag_max",
                    "value": 3.8903121948242188,
                    "unit": "MB",
                    "report": "lower_is_better"
                },
                {
                    "name": "lsn_write_lag_avg",
                    "value": 1.3674389675325234,
                    "unit": "MB",
                    "report": "lower_is_better"
                },
                {
                    "name": "lsn_write_lag_stdev",
                    "value": 0.6556716607228185,
                    "unit": "MB",
                    "report": "lower_is_better"
                },
                {
                    "name": "read_latency_max",
                    "value": 0.199010652009747,
                    "unit": "s",
                    "report": "lower_is_better"
                },
                {
                    "name": "read_latency_avg",
                    "value": 0.039691618260367746,
                    "unit": "s",
                    "report": "lower_is_better"
                },
                {
                    "name": "read_latency_stdev",
                    "value": 0.031121638168429458,
                    "unit": "s",
                    "report": "lower_is_better"
                }
            ]
        },
        {
            "suit": "test_runner/performance/test_wal_backpressure.py::test_heavy_write_workload[neon_on-10-5-5]",
            "total_duration": 252.90413072900265,
            "data": [
                {
                    "name": "run_duration",
                    "value": 250.55082786698767,
                    "unit": "s",
                    "report": "lower_is_better"
                },
                {
                    "name": "lsn_write_lag_max",
                    "value": 4.271461486816406,
                    "unit": "MB",
                    "report": "lower_is_better"
                },
                {
                    "name": "lsn_write_lag_avg",
                    "value": 1.4223304839723139,
                    "unit": "MB",
                    "report": "lower_is_better"
                },
                {
                    "name": "lsn_write_lag_stdev",
                    "value": 0.7795653921507917,
                    "unit": "MB",
                    "report": "lower_is_better"
                },
                {
                    "name": "read_latency_max",
                    "value": 0.6894765160104726,
                    "unit": "s",
                    "report": "lower_is_better"
                },
                {
                    "name": "read_latency_avg",
                    "value": 0.0552248929332166,
                    "unit": "s",
                    "report": "lower_is_better"
                },
                {
                    "name": "read_latency_stdev",
                    "value": 0.07683711123554608,
                    "unit": "s",
                    "report": "lower_is_better"
                }
            ]
        },
        {
            "suit": "test_runner/performance/test_wal_backpressure.py::test_pgbench_simple_update_workload[vanilla-45-100]",
            "total_duration": 62.757699673995376,
            "data": [
                {
                    "name": "run_duration",
                    "value": 45.66986332999659,
                    "unit": "s",
                    "report": "lower_is_better"
                },
                {
                    "name": "read_latency_max",
                    "value": 0.011697750000166707,
                    "unit": "s",
                    "report": "lower_is_better"
                },
                {
                    "name": "read_latency_avg",
                    "value": 0.0011609973032887945,
                    "unit": "s",
                    "report": "lower_is_better"
                },
                {
                    "name": "read_latency_stdev",
                    "value": 0.0022257114949416476,
                    "unit": "s",
                    "report": "lower_is_better"
                }
            ]
        },
        {
            "suit": "test_runner/performance/test_wal_backpressure.py::test_pgbench_simple_update_workload[neon_off-45-100]",
            "total_duration": 133.18523775599897,
            "data": [
                {
                    "name": "run_duration",
                    "value": 47.74163370300084,
                    "unit": "s",
                    "report": "lower_is_better"
                },
                {
                    "name": "lsn_write_lag_max",
                    "value": 0.5694580078125,
                    "unit": "MB",
                    "report": "lower_is_better"
                },
                {
                    "name": "lsn_write_lag_avg",
                    "value": 0.26201709111531574,
                    "unit": "MB",
                    "report": "lower_is_better"
                },
                {
                    "name": "lsn_write_lag_stdev",
                    "value": 0.14115463269868683,
                    "unit": "MB",
                    "report": "lower_is_better"
                },
                {
                    "name": "read_latency_max",
                    "value": 0.04798836799454875,
                    "unit": "s",
                    "report": "lower_is_better"
                },
                {
                    "name": "read_latency_avg",
                    "value": 0.0066760878116838285,
                    "unit": "s",
                    "report": "lower_is_better"
                },
                {
                    "name": "read_latency_stdev",
                    "value": 0.011288361180224481,
                    "unit": "s",
                    "report": "lower_is_better"
                }
            ]
        },
        {
            "suit": "test_runner/performance/test_wal_backpressure.py::test_pgbench_simple_update_workload[neon_on-45-100]",
            "total_duration": 159.94475427799625,
            "data": [
                {
                    "name": "run_duration",
                    "value": 53.3326220500021,
                    "unit": "s",
                    "report": "lower_is_better"
                },
                {
                    "name": "read_latency_max",
                    "value": 0.03534693698748015,
                    "unit": "s",
                    "report": "lower_is_better"
                },
                {
                    "name": "read_latency_avg",
                    "value": 0.005550656623628763,
                    "unit": "s",
                    "report": "lower_is_better"
                },
                {
                    "name": "read_latency_stdev",
                    "value": 0.008413308779978037,
                    "unit": "s",
                    "report": "lower_is_better"
                },
                {
                    "name": "lsn_write_lag_max",
                    "value": 0.5845718383789062,
                    "unit": "MB",
                    "report": "lower_is_better"
                },
                {
                    "name": "lsn_write_lag_avg",
                    "value": 0.2345804285120081,
                    "unit": "MB",
                    "report": "lower_is_better"
                },
                {
                    "name": "lsn_write_lag_stdev",
                    "value": 0.1431012277972154,
                    "unit": "MB",
                    "report": "lower_is_better"
                }
            ]
        },
        {
            "suit": "test_runner/performance/test_wal_backpressure.py::test_pgbench_intensive_init_workload[vanilla-1000]",
            "total_duration": 111.11815922499227,
            "data": [
                {
                    "name": "run_duration",
                    "value": 110.13142372400034,
                    "unit": "s",
                    "report": "lower_is_better"
                },
                {
                    "name": "read_latency_max",
                    "value": 0.024757624996709637,
                    "unit": "s",
                    "report": "lower_is_better"
                },
                {
                    "name": "read_latency_avg",
                    "value": 0.008374112481463023,
                    "unit": "s",
                    "report": "lower_is_better"
                },
                {
                    "name": "read_latency_stdev",
                    "value": 0.0027889297834893935,
                    "unit": "s",
                    "report": "lower_is_better"
                }
            ]
        },
        {
            "suit": "test_runner/performance/test_wal_backpressure.py::test_pgbench_intensive_init_workload[neon_off-1000]",
            "total_duration": 72.79940810000699,
            "data": [
                {
                    "name": "run_duration",
                    "value": 71.25485036500322,
                    "unit": "s",
                    "report": "lower_is_better"
                },
                {
                    "name": "read_latency_max",
                    "value": 4.237075156008359,
                    "unit": "s",
                    "report": "lower_is_better"
                },
                {
                    "name": "read_latency_avg",
                    "value": 1.2197413027820403,
                    "unit": "s",
                    "report": "lower_is_better"
                },
                {
                    "name": "read_latency_stdev",
                    "value": 0.8966066516309477,
                    "unit": "s",
                    "report": "lower_is_better"
                },
                {
                    "name": "lsn_write_lag_max",
                    "value": 15.104537963867188,
                    "unit": "MB",
                    "report": "lower_is_better"
                },
                {
                    "name": "lsn_write_lag_avg",
                    "value": 3.170900870060575,
                    "unit": "MB",
                    "report": "lower_is_better"
                },
                {
                    "name": "lsn_write_lag_stdev",
                    "value": 4.006588610127519,
                    "unit": "MB",
                    "report": "lower_is_better"
                }
            ]
        },
        {
            "suit": "test_runner/performance/test_wal_backpressure.py::test_pgbench_intensive_init_workload[neon_on-1000]",
            "total_duration": 128.11185382198892,
            "data": [
                {
                    "name": "run_duration",
                    "value": 126.0801131890039,
                    "unit": "s",
                    "report": "lower_is_better"
                },
                {
                    "name": "lsn_write_lag_max",
                    "value": 15.104652404785156,
                    "unit": "MB",
                    "report": "lower_is_better"
                },
                {
                    "name": "lsn_write_lag_avg",
                    "value": 11.473915160648406,
                    "unit": "MB",
                    "report": "lower_is_better"
                },
                {
                    "name": "lsn_write_lag_stdev",
                    "value": 4.534341906715657,
                    "unit": "MB",
                    "report": "lower_is_better"
                },
                {
                    "name": "read_latency_max",
                    "value": 25.444866635996732,
                    "unit": "s",
                    "report": "lower_is_better"
                },
                {
                    "name": "read_latency_avg",
                    "value": 11.696347177903226,
                    "unit": "s",
                    "report": "lower_is_better"
                },
                {
                    "name": "read_latency_stdev",
                    "value": 8.30726115117373,
                    "unit": "s",
                    "report": "lower_is_better"
                }
            ]
        },
        {
            "suit": "test_runner/performance/test_write_amplification.py::test_write_amplification[vanilla]",
            "total_duration": 3.5366990369948326,
            "data": [
                {
                    "name": "run",
                    "value": 3.527807368998765,
                    "unit": "s",
                    "report": "lower_is_better"
                },
                {
                    "name": "data_size",
                    "value": 260.681435585022,
                    "unit": "MB",
                    "report": "lower_is_better"
                },
                {
                    "name": "wal_size",
                    "value": 32.0,
                    "unit": "MB",
                    "report": "lower_is_better"
                }
            ]
        },
        {
            "suit": "test_runner/performance/test_write_amplification.py::test_write_amplification[neon]",
            "total_duration": 14.472342429013224,
            "data": [
                {
                    "name": "run",
                    "value": 14.458425881995936,
                    "unit": "s",
                    "report": "lower_is_better"
                },
                {
                    "name": "pageserver_writes",
                    "value": 678,
                    "unit": "MB",
                    "report": "lower_is_better"
                },
                {
                    "name": "size",
                    "value": 376.57861328125,
                    "unit": "MB",
                    "report": "lower_is_better"
                },
                {
                    "name": "data_uploaded",
                    "value": 376.953125,
                    "unit": "MB",
                    "report": "lower_is_better"
                },
                {
                    "name": "num_files_uploaded",
                    "value": 25,
                    "unit": "",
                    "report": "lower_is_better"
                }
            ]
        }
    ]
}