{
    "revision": "e6a5b370eb1a19b0a3cdbc584970a92b3c2fc444",
    "platform": "neon-captest-reuse",
    "result": [
        {
            "suit": "test_runner/performance/test_perf_pgbench.py::test_pgbench_remote_init[3600-684]",
            "total_duration": 2283.0999480070022,
            "data": [
                {
                    "name": "scale",
                    "value": 684,
                    "unit": "",
                    "report": "test_param"
                },
                {
                    "name": "init.start_timestamp",
                    "value": 1670945533,
                    "unit": "",
                    "report": "test_param"
                },
                {
                    "name": "init.end_timestamp",
                    "value": 1670947816,
                    "unit": "",
                    "report": "test_param"
                },
                {
                    "name": "init.duration",
                    "value": 2283.098950186002,
                    "unit": "s",
                    "report": "lower_is_better"
                },
                {
                    "name": "init.drop_tables",
                    "value": 0.05,
                    "unit": "s",
                    "report": "lower_is_better"
                },
                {
                    "name": "init.create_tables",
                    "value": 0.05,
                    "unit": "s",
                    "report": "lower_is_better"
                },
                {
                    "name": "init.client_side_generate",
                    "value": 72.89,
                    "unit": "s",
                    "report": "lower_is_better"
                },
                {
                    "name": "init.vacuum",
                    "value": 1708.09,
                    "unit": "s",
                    "report": "lower_is_better"
                },
                {
                    "name": "init.primary_keys",
                    "value": 501.95,
                    "unit": "s",
                    "report": "lower_is_better"
                }
            ]
        }
    ]
}